pycallgraphix/__init__.py
pycallgraphix/driver.py
pycallgraphix/wrapper.py
test/__init__.py
test/test_store_calls.py
test/test_store_funcs.py
pycallgraphix-1.0.2.dist-info/LICENSE.txt
pycallgraphix-1.0.2.dist-info/METADATA
pycallgraphix-1.0.2.dist-info/WHEEL
pycallgraphix-1.0.2.dist-info/top_level.txt
pycallgraphix-1.0.2.dist-info/RECORD
