Metadata-Version: 2.1
Name: pycallgraphix
Version: 1.0.2
Summary: pycallgraphix is an extension of standard call graph python packages that enables users to independently select the functions they wish to include in visualizations by simply applying a function wrapper.
Home-page: https://github.com/FZJ-IEK3-VSA/pycallgraphix
Author: Matthew Keller, Katharina Rieck
Author-email: ma.keller@fz-juelich.de, k.rieck@fz-juelich.de
License: MIT License
Keywords: call graph,wrapper,visual,pycall,graphix
Classifier: License :: OSI Approved :: MIT License
Classifier: Natural Language :: English
Classifier: Operating System :: OS Independent
Classifier: Programming Language :: Python
Classifier: Programming Language :: Python :: 3
Requires-Python: >=3.7
License-File: LICENSE.txt
Requires-Dist: pydot >=1.4.2
Requires-Dist: seaborn >=0.11.2
